pypgn/__init__.py
pypgn/game.py
pypgn/game_utils.py
pypgn-0.5.1.dist-info/LICENSE
pypgn-0.5.1.dist-info/METADATA
pypgn-0.5.1.dist-info/WHEEL
pypgn-0.5.1.dist-info/top_level.txt
pypgn-0.5.1.dist-info/RECORD
