Metadata-Version: 2.1
Name: pypgn
Version: 0.5.1
Summary: Library for parsing and manipulating PGN format files.
Home-page: https://github.com/DaniruKun/pypgn
Author: Daniils Petrovs
Author-email: thedanpetrov@gmail.com
License: MPL-2.0
Keywords: pgn,chess,game,notation
Platform: UNKNOWN
Classifier: Development Status :: 3 - Alpha
Classifier: Intended Audience :: Developers
Classifier: Topic :: Text Processing
Classifier: Programming Language :: Python :: 3
Classifier: Programming Language :: Python :: 3.6
Classifier: Programming Language :: Python :: 3.7
Classifier: Programming Language :: Python :: 3.8
